statfinder/__init__.py
statfinder-0.0.0.dist-info/METADATA
statfinder-0.0.0.dist-info/WHEEL
statfinder-0.0.0.dist-info/top_level.txt
statfinder-0.0.0.dist-info/RECORD
